README
setup.py
django_messages_framework/__init__.py
django_messages_framework/api.py
django_messages_framework/constants.py
django_messages_framework/context_processors.py
django_messages_framework/middleware.py
django_messages_framework/models.py
django_messages_framework/utils.py
django_messages_framework.egg-info/PKG-INFO
django_messages_framework.egg-info/SOURCES.txt
django_messages_framework.egg-info/dependency_links.txt
django_messages_framework.egg-info/top_level.txt
django_messages_framework/backport/__init__.py
django_messages_framework/backport/hashcompat.py
django_messages_framework/backport/http.py
django_messages_framework/storage/__init__.py
django_messages_framework/storage/base.py
django_messages_framework/storage/cookie.py
django_messages_framework/storage/fallback.py
django_messages_framework/storage/session.py
django_messages_framework/storage/user_messages.py
django_messages_framework/tests/__init__.py
django_messages_framework/tests/base.py
django_messages_framework/tests/cookie.py
django_messages_framework/tests/fallback.py
django_messages_framework/tests/middleware.py
django_messages_framework/tests/session.py
django_messages_framework/tests/urls.py
django_messages_framework/tests/user_messages.py