Metadata-Version: 1.0
Name: django-messages-framework
Version: 1.0.0
Summary: Backport of django (dev)'s messages framework that works with 1.1.1.
Home-page: http://github.com/mikexstudios/django-messages-framework
Author: Michael Huynh
Author-email: mike@mikexstudios.com
License: UNKNOWN
Platform: UNKNOWN
Classifier: Programming Language :: Python
Classifier: Framework :: Django
Classifier: License :: OSI Approved :: BSD License
